dict2dc/__init__.py
dict2dc/dc2json.py
dict2dc/dc2query.py
dict2dc/dict2dc.py
dict2dc/py.typed
dict2dc/models/__init__.py
dict2dc/models/base.py
dict2dc/models/parsing.py
dict2dc/models/requests.py
dict2dc/utils/__init__.py
dict2dc/utils/types.py
dict2dc-0.1.2.dist-info/METADATA
dict2dc-0.1.2.dist-info/WHEEL
dict2dc-0.1.2.dist-info/licenses/LICENSE
dict2dc-0.1.2.dist-info/RECORD
