Metadata-Version: 2.4
Name: dict2dc
Version: 0.1.2
Summary: Helpers to parse dicts, e.g., from JSON parsing, to dataclasses.
Project-URL: Homepage, https://github.com/twwd/dict2dc
Project-URL: Issues, https://github.com/twwd/dict2dc/issues
Author-email: Tim Walter <tim.walter@iteratec.com>
License-Expression: MIT
License-File: LICENSE
Keywords: conversion,dataclass,dataclasses,dict,json,parsing,serialization
Classifier: License :: OSI Approved :: MIT License
Classifier: Operating System :: OS Independent
Classifier: Programming Language :: Python :: 3
Classifier: Topic :: File Formats :: JSON
Requires-Python: >=3.12
